gendiff/__init__.py
gendiff/data.py
gendiff/differ.py
gendiff/generate_diff.py
gendiff/parser.py
gendiff/formatters/__init__.py
gendiff/formatters/json.py
gendiff/formatters/plain.py
gendiff/formatters/stylish.py
gendiff/scripts/__init__.py
gendiff/scripts/gendiff.py
tests/__init__.py
tests/test_generate_diff.py
gendiff_dmitriev-0.1.0.dist-info/METADATA
gendiff_dmitriev-0.1.0.dist-info/WHEEL
gendiff_dmitriev-0.1.0.dist-info/entry_points.txt
gendiff_dmitriev-0.1.0.dist-info/top_level.txt
gendiff_dmitriev-0.1.0.dist-info/RECORD
