Metadata-Version: 2.1
Name: gendiff-dmitriev
Version: 0.1.0
Summary: UNKNOWN
Home-page: UNKNOWN
License: UNKNOWN
Platform: UNKNOWN
Classifier: Programming Language :: Python :: 3
Classifier: License :: OSI Approved :: MIT License
Classifier: Operating System :: OS Independent
Requires-Python: >=3.10
Requires-Dist: PyYAML (>=6.0.1)
Requires-Dist: pytest (>=8.3.2)
